move_fcg_analyzer
